cdk_cloudformation_karte_eventbridge_documentdb_module/__init__.py
cdk_cloudformation_karte_eventbridge_documentdb_module/py.typed
cdk_cloudformation_karte_eventbridge_documentdb_module/_jsii/__init__.py
cdk_cloudformation_karte_eventbridge_documentdb_module/_jsii/karte-eventbridge-documentdb-module@1.0.2-alpha.7.jsii.tgz
cdk_cloudformation_karte_eventbridge_documentdb_module-1.0.2a7.dist-info/LICENSE
cdk_cloudformation_karte_eventbridge_documentdb_module-1.0.2a7.dist-info/METADATA
cdk_cloudformation_karte_eventbridge_documentdb_module-1.0.2a7.dist-info/WHEEL
cdk_cloudformation_karte_eventbridge_documentdb_module-1.0.2a7.dist-info/top_level.txt
cdk_cloudformation_karte_eventbridge_documentdb_module-1.0.2a7.dist-info/RECORD
